[
  {
    "track_id": "2jHEySxCzzODFWmPzt084L",
    "track_name": "18 ~eighteen~",
    "artist": "Masaharu Fukuyama",
    "image_url": "https://i.scdn.co/image/ab67616d0000b2731f2560ca505e7afa43232461",
    "preview_url": null
  },
  {
    "track_id": "0R3LjmIZg8MiBlf3LdYjcD",
    "track_name": "Too Much Heaven",
    "artist": "Gail Blanco",
    "image_url": "https://i.scdn.co/image/ab67616d0000b273b310d8a8aa896c2dd477c05d",
    "preview_url": null
  },
  {
    "track_id": "1T7Tqsfkz0Ntbwta2hHebY",
    "track_name": "Fate of a Coward",
    "artist": "Days N Daze",
    "image_url": "https://i.scdn.co/image/ab67616d0000b273d150c9a7fb2b8821c56a17e6",
    "preview_url": null
  },
  {
    "track_id": "7MlPySldFcJ9R3mSFvGV4y",
    "track_name": "彼方で",
    "artist": "Masaharu Fukuyama",
    "image_url": "https://i.scdn.co/image/ab67616d0000b273a7521de33a43dd7897c8b284",
    "preview_url": null
  },
  {
    "track_id": "1wflx5YklLYToaIbXkrZSq",
    "track_name": "Somebody Loved",
    "artist": "Kina Grannis",
    "image_url": "https://i.scdn.co/image/ab67616d0000b2733d3440c6e7183d85853cd7b8",
    "preview_url": null
  },
  {
    "track_id": "68HbD7rEFTlnJy4UWSpySY",
    "track_name": "世界中の誰よりきっと",
    "artist": "Mone Kamishiraishi",
    "image_url": "https://i.scdn.co/image/ab67616d0000b2730c5c6ddcd6d98038987d873c",
    "preview_url": null
  },
  {
    "track_id": "1CtfA9JkJ5cJQgpO7wEj4V",
    "track_name": "He's A Pirate (From \"Pirates of the Caribbean\")",
    "artist": "Beyond The Guitar",
    "image_url": "https://i.scdn.co/image/ab67616d0000b2733e184ed085f6e5c8789bbf80",
    "preview_url": null
  },
  {
    "track_id": "27hFQQS3cVUmIK3ser5bpu",
    "track_name": "More Than Gravity",
    "artist": "Colin & Caroline",
    "image_url": "https://i.scdn.co/image/ab67616d0000b273d18fbe9f99501da5982245c1",
    "preview_url": null
  },
  {
    "track_id": "5hVKGw1OXBCEZgRWFUilk7",
    "track_name": "Still Falling For You - Acoustic",
    "artist": "Sara Farell;Simon Samaeng",
    "image_url": "https://i.scdn.co/image/ab67616d0000b273b0337012f518c200fa212190",
    "preview_url": null
  },
  {
    "track_id": "2PIlBukQ6limukVR8Ubb5o",
    "track_name": "Please Don't Say You Love Me",
    "artist": "Gabrielle Aplin",
    "image_url": "https://i.scdn.co/image/ab67616d0000b27391df3331ecc28d6d199255e9",
    "preview_url": null
  }
]